distributions_bizmaercq/__init__.py
distributions_bizmaercq/binomial.py
distributions_bizmaercq/distribution.py
distributions_bizmaercq/gaussian.py
distributions_bizmaercq-1.0.dist-info/METADATA
distributions_bizmaercq-1.0.dist-info/WHEEL
distributions_bizmaercq-1.0.dist-info/top_level.txt
distributions_bizmaercq-1.0.dist-info/RECORD
