Metadata-Version: 2.1
Name: distributions-bizmaercq
Version: 1.0
Summary: Gausian and Binomial distribution
Home-page: UNKNOWN
Author: Bismark Adomako
Author-email: bismark.adomako@bizmaercq.com
License: UNKNOWN
Platform: UNKNOWN
